vaillant_netatmo_api_mod/__init__.py
vaillant_netatmo_api_mod/auth.py
vaillant_netatmo_api_mod/auth_test.py
vaillant_netatmo_api_mod/base.py
vaillant_netatmo_api_mod/errors.py
vaillant_netatmo_api_mod/errors_test.py
vaillant_netatmo_api_mod/thermostat.py
vaillant_netatmo_api_mod/thermostat_auth.py
vaillant_netatmo_api_mod/thermostat_program_test.py
vaillant_netatmo_api_mod/thermostat_test.py
vaillant_netatmo_api_mod/time.py
vaillant_netatmo_api_mod/token.py
vaillant_netatmo_api_mod/token_test.py
vaillant_netatmo_api_mod-0.10.0.dist-info/LICENSE
vaillant_netatmo_api_mod-0.10.0.dist-info/METADATA
vaillant_netatmo_api_mod-0.10.0.dist-info/WHEEL
vaillant_netatmo_api_mod-0.10.0.dist-info/top_level.txt
vaillant_netatmo_api_mod-0.10.0.dist-info/RECORD
