Metadata-Version: 2.1
Name: vaillant-netatmo-api-mod
Version: 0.10.0
Summary: Python 3 library for managing Vaillant thermostats using the Netatmo API.
Home-page: https://github.com/Przemko92/vaillant-netatmo-api
Author: Mislav Mandaric
Project-URL: Bug Tracker, https://github.com/Przemko92/vaillant-netatmo-api/issues
Classifier: Programming Language :: Python :: 3
Classifier: License :: OSI Approved :: MIT License
Classifier: Operating System :: OS Independent
Requires-Python: >=3.8
License-File: LICENSE
Requires-Dist: httpx (>=0.18.2)
Requires-Dist: tenacity (>=8.0.1)
